SRL-0.1.0.dist-info/DESCRIPTION.rst
SRL-0.1.0.dist-info/METADATA
SRL-0.1.0.dist-info/RECORD
SRL-0.1.0.dist-info/WHEEL
SRL-0.1.0.dist-info/metadata.json
SRL-0.1.0.dist-info/top_level.txt
srl/__init__.py
srl/_compat.py
srl/builder.py
srl/errors.py
srl/srl.py
srl/parsers/__init__.py
srl/parsers/parse.py
srl/parsers/parsetab.py
srl/utils/__init__.py
srl/utils/lex.py
srl/utils/yacc.py
