Metadata-Version: 2.0
Name: SRL
Version: 0.1.0
Summary: Python implementation of SRL.
Home-page: https://github.com/SimpleRegex/SRL-Python
Author: Simple Regex Language
Author-email: UNKNOWN
License: MIT
Keywords: re,regex,srl,simpleregex
Platform: UNKNOWN
Classifier: Development Status :: 2 - Pre-Alpha
Classifier: Intended Audience :: Developers
Classifier: Natural Language :: English
Classifier: Programming Language :: Python :: 2
Classifier: Programming Language :: Python :: 2.6
Classifier: Programming Language :: Python :: 2.7
Classifier: Programming Language :: Python :: 3
Classifier: Programming Language :: Python :: 3.3
Classifier: Programming Language :: Python :: 3.4
Classifier: Programming Language :: Python :: 3.5
